[
{  "ColumnName":"REPORT_TIME", "Type" : "TIMESTAMP" },
{  "ColumnName":"GUMMEI_MCC", "Type" : "VARCHAR(4)" },
{  "ColumnName":"GUMMEI_MNC", "Type" : "VARCHAR(4)" },
{  "ColumnName":"GUMMEI_GROUP_ID", "Type" : "SMALLINT" },
{  "ColumnName":"GUMMEI_CODE", "Type" : "TINYINT" },
{  "ColumnName":"IMSI", "Type" : "VARCHAR(16)" },
{  "ColumnName":"GUTI_MCC", "Type" : "VARCHAR(4)" },
{  "ColumnName":"GUTI_MNC", "Type" : "VARCHAR(4)" },
{  "ColumnName":"GUTI_GROUP_ID", "Type" : "SMALLINT" },
{  "ColumnName":"GUTI_CODE", "Type" : "TINYINT" },
{  "ColumnName":"GUTI_MTMSI", "Type" : "INTEGER" },
{  "ColumnName":"ATTACH_TIME", "Type" : "TIMESTAMP" },
{  "ColumnName":"TAI_MCC", "Type" : "VARCHAR(4)" },
{  "ColumnName":"TAI_MNC", "Type" : "VARCHAR(4)" },
{  "ColumnName":"TAI_TAC", "Type" : "SMALLINT" },
{  "ColumnName":"ROAMING_STATUS", "Type" : "TINYINT" },
{  "ColumnName":"GLOBAL_ENODEB_MCC", "Type" : "VARCHAR(4)" },
{  "ColumnName":"GLOBAL_ENODEB_MNC", "Type" : "VARCHAR(4)" },
{  "ColumnName":"GLOBAL_ENODEB_ID", "Type" : "INTEGER" },
{  "ColumnName":"CPPU_LOGICAL_ADDRESS", "Type" : "SMALLINT" },
{  "ColumnName":"MMDU_LOGICAL_ADDRESS", "Type" : "SMALLINT" },
{  "ColumnName":"IPDU_LOGICAL_ADDRESS", "Type" : "SMALLINT" },
{  "ColumnName":"MME_S1AP_ID", "Type" : "INTEGER" },
{  "ColumnName":"ENODEB_S1AP_ID", "Type" : "INTEGER" },
{  "ColumnName":"CAUSE_PROC", "Type" : "TINYINT" },
{  "ColumnName":"INTERNAL_CAUSE", "Type" : "INTEGER" },
{  "ColumnName":"S1AP_CAUSE", "Type" : "TINYINT" },
{  "ColumnName":"S11_CAUSE_CODE", "Type" : "TINYINT" },
{  "ColumnName":"SGW_CONTROL_PLANE_TEID_PRESENCE", "Type" : "TINYINT" },
{  "ColumnName":"SGW_CONTROL_PLANE_TEID_VALUE", "Type" : "INTEGER" },
{  "ColumnName":"SGW_CONTROL_PLANE_TEID_IP_ADDRESS_VERSION", "Type" : "TINYINT" },
{  "ColumnName":"SGW_CONTROL_PLANE_TEID_IP_ADDRESS", "Type" : "VARCHAR(40)" },
{  "ColumnName":"TEID_PRESENCE", "Type" : "TINYINT" },
{  "ColumnName":"TEID_VALUE", "Type" : "INTEGER" },
{  "ColumnName":"CHARGING_CHARACTERISTICS", "Type" : "TINYINT" },
{  "ColumnName":"MSISDN_INDICATORS", "Type" : "TINYINT" },
{  "ColumnName":"MSISDN", "Type" : "VARCHAR(18)" },
{  "ColumnName":"IMEI_IMEISV", "Type" : "VARCHAR(16)" },
{  "ColumnName":"OLD_GUTI_MCC", "Type" : "VARCHAR(4)" },
{  "ColumnName":"OLD_GUTI_MNC", "Type" : "VARCHAR(4)" },
{  "ColumnName":"OLD_GUTI_GROUP_ID", "Type" : "SMALLINT" },
{  "ColumnName":"OLD_GUTI_CODE", "Type" : "TINYINT" },
{  "ColumnName":"OLD_GUTI_MTMSI", "Type" : "INTEGER" },
{  "ColumnName":"UE_RADIO_CAPABILITY_INFORMATION", "Type" : "BINARY" },
{  "ColumnName":"UE_CORE_NETWORK_CAPABILITY_INFORMATION", "Type" : "INTEGER" },
{  "ColumnName":"DESTINATION_REALM", "Type" : "VARCHAR(50)" },
{  "ColumnName":"HOST_NAME", "Type" : "VARCHAR(111)" },
{  "ColumnName":"LAST_VISITED_TAI_MCC", "Type" : "VARCHAR(4)" },
{  "ColumnName":"LAST_VISITED_TAI_MNC", "Type" : "VARCHAR(4)" },
{  "ColumnName":"LAST_VISITED_TAI_TAC", "Type" : "SMALLINT" },
{  "ColumnName":"ECGI_MCC", "Type" : "VARCHAR(4)" },
{  "ColumnName":"ECGI_MNC", "Type" : "VARCHAR(4)" },
{  "ColumnName":"ECGI", "Type" : "INTEGER" },
{  "ColumnName":"EMM_CAUSE", "Type" : "TINYINT" },
{  "ColumnName":"ECM_IN_STATE", "Type" : "TINYINT" },
{  "ColumnName":"ECM_OUT_STATE", "Type" : "TINYINT" },
{  "ColumnName":"EMM_IN_STATE", "Type" : "TINYINT" },
{  "ColumnName":"EMM_OUT_STATE", "Type" : "TINYINT" },
{  "ColumnName":"AUTHENTICATION_DONE_IN_PROC", "Type" : "TINYINT" },
{  "ColumnName":"IMEI_CHECK_INFO", "Type" : "TINYINT" },
{  "ColumnName":"INTEGRITY_PROTECTION_ALG", "Type" : "TINYINT" },
{  "ColumnName":"CONFIDENTIALITY_PROTECTION_ALG", "Type" : "TINYINT" },
{  "ColumnName":"LINKED_MM_PROC", "Type" : "TINYINT" },
{  "ColumnName":"ESM_CAUSE", "Type" : "TINYINT" },
{  "ColumnName":"BEARER_CREATION_TIME", "Type" : "TIMESTAMP" },
{  "ColumnName":"HSS_PDN_TYPE", "Type" : "TINYINT" },
{  "ColumnName":"BEARER_PDN_TYPE", "Type" : "TINYINT" },
{  "ColumnName":"BEARER_PDN_IPV4_ADDRESS", "Type" : "VARCHAR(40)" },
{  "ColumnName":"BEARER_PDN_IPV6_ADDRESS", "Type" : "VARCHAR(40)" },
{  "ColumnName":"APN", "Type" : "VARCHAR(126)" },
{  "ColumnName":"EPS_BEARER_ID", "Type" : "TINYINT" },
{  "ColumnName":"EPS_LINKED_BEARER_ID", "Type" : "TINYINT" },
{  "ColumnName":"REQUESTED_UE_QCI", "Type" : "TINYINT" },
{  "ColumnName":"REQUESTED_MBR_UPLINK", "Type" : "INTEGER" },
{  "ColumnName":"REQUESTED_MBR_DOWNLINK", "Type" : "INTEGER" },
{  "ColumnName":"REQUESTED_GBR_UPLINK", "Type" : "INTEGER" },
{  "ColumnName":"REQUESTED_GBR_DOWNLINK", "Type" : "INTEGER" },
{  "ColumnName":"ALLOWED_APN_AMBR_UPLINK", "Type" : "INTEGER" },
{  "ColumnName":"ALLOWED_APN_AMBR_DOWNLINK", "Type" : "INTEGER" },
{  "ColumnName":"ALLOWED_APN_QCI", "Type" : "TINYINT" },
{  "ColumnName":"ALLOWED_ARP_PRIORITY_LEVEL", "Type" : "TINYINT" },
{  "ColumnName":"ALLOWED_ARP_PRE_EMPTION_CAPABILITY", "Type" : "TINYINT" },
{  "ColumnName":"ALLOWED_ARP_PRE_EMPTION_VULNERABILITY", "Type" : "TINYINT" },
{  "ColumnName":"ALLOWED_UE_AMBR_UPLINK", "Type" : "INTEGER" },
{  "ColumnName":"ALLOWED_UE_AMBR_DOWNLINK", "Type" : "INTEGER" },
{  "ColumnName":"NEGOTIATED_APN_AMBR_UPLINK", "Type" : "INTEGER" },
{  "ColumnName":"NEGOTIATED_APN_AMBR_DOWNLINK", "Type" : "INTEGER" },
{  "ColumnName":"NEGOTIATED_APN_QCI", "Type" : "TINYINT" },
{  "ColumnName":"NEGOTIATED_ARP_PRIORITY_LEVEL", "Type" : "TINYINT" },
{  "ColumnName":"NEGOTIATED_ARP_PRE_EMPTION_CAPABILITY", "Type" : "TINYINT" },
{  "ColumnName":"NEGOTIATED_ARP_PRE_EMPTION_VULNERABILITY", "Type" : "TINYINT" },
{  "ColumnName":"NEGOTIATED_UE_AMBR_UPLINK", "Type" : "INTEGER" },
{  "ColumnName":"NEGOTIATED_UE_AMBR_DOWNLINK", "Type" : "INTEGER" },
{  "ColumnName":"NEGOTIATED_GBR_UPLINK", "Type" : "INTEGER" },
{  "ColumnName":"NEGOTIATED_GBR_DOWNLINK", "Type" : "INTEGER" },
{  "ColumnName":"SGW_USER_PLANE_TEID_PRESENCE", "Type" : "TINYINT" },
{  "ColumnName":"SGW_USER_PLANE_TEID_VALUE", "Type" : "INTEGER" },
{  "ColumnName":"SGW_USER_PLANE_TEID_IP_ADDRESS_VERSION", "Type" : "TINYINT" },
{  "ColumnName":"SGW_USER_PLANE_TEID_IP_ADDRESS", "Type" : "VARCHAR(40)" },
{  "ColumnName":"PDN_GATEWAY_CONTROL_PLANE_TEID_PRESENCE", "Type" : "TINYINT" },
{  "ColumnName":"PDN_GATEWAY_CONTROL_PLANE_TEID_VALUE", "Type" : "INTEGER" },
{  "ColumnName":"PDN_GATEWAY_CONTROL_PLANE_TEID_IP_ADDRESS_VERSION", "Type" : "TINYINT" },
{  "ColumnName":"PDN_GATEWAY_CONTROL_PLANE_TEID_IP_ADDRESS", "Type" : "VARCHAR(40)" },
{  "ColumnName":"PDN_GATEWAY_USER_PLANE_TEID_PRESENCE", "Type" : "TINYINT" },
{  "ColumnName":"PDN_GATEWAY_USER_PLANE_TEID_VALUE", "Type" : "INTEGER" },
{  "ColumnName":"PDN_GATEWAY_USER_PLANE_TEID_IP_ADDRESS_VERSION", "Type" : "TINYINT" },
{  "ColumnName":"PDN_GATEWAY_USER_PLANE_TEID_IP_ADDRESS", "Type" : "VARCHAR(40)" },
{  "ColumnName":"ENODEB_USER_PLANE_TEID_PRESENCE", "Type" : "TINYINT" },
{  "ColumnName":"ENODEB_USER_PLANE_TEID_VALUE", "Type" : "INTEGER" },
{  "ColumnName":"ENODEB_USER_PLANE_TEID_IP_ADDRESS_VERSION", "Type" : "TINYINT" },
{  "ColumnName":"ENODEB_USER_PLANE_TEID_IP_ADDRESS", "Type" : "VARCHAR(40)" },
{  "ColumnName":"REQUESTED_PDN_TYPE", "Type" : "TINYINT" },
{  "ColumnName":"MME_REPORT_TYPE", "Type" : "TINYINT" },
{  "ColumnName":"SOURCE_ID", "Type" : "INTEGER" }
]

